Metadata-Version: 2.4
Name: flask-openapi3-swagger
Version: 5.31.0
Summary: Provide Swagger UI for flask-openapi3.
Project-URL: Homepage, https://github.com/luolingchun/flask-openapi3-plugins/tree/master/flask-openapi3-swagger
Project-URL: Documentation, https://luolingchun.github.io/flask-openapi3/latest/Usage/UI_Templates/
Maintainer-email: llc <luolingchun@outlook.com>
License: MIT
Classifier: Development Status :: 5 - Production/Stable
Classifier: Environment :: Web Environment
Classifier: Framework :: Flask
Classifier: Intended Audience :: Developers
Classifier: License :: OSI Approved :: MIT License
Classifier: Operating System :: OS Independent
Classifier: Programming Language :: Python
Classifier: Programming Language :: Python :: 3
Classifier: Programming Language :: Python :: 3 :: Only
Requires-Python: >=3.8
Requires-Dist: flask-openapi3
